.version
2mp4/__init__.py
2mp4-1.0.1.dist-info/DESCRIPTION.rst
2mp4-1.0.1.dist-info/METADATA
2mp4-1.0.1.dist-info/RECORD
2mp4-1.0.1.dist-info/WHEEL
2mp4-1.0.1.dist-info/entry_points.txt
2mp4-1.0.1.dist-info/metadata.json
2mp4-1.0.1.dist-info/top_level.txt
py2mp4/__init__.py
v2mp4/__init__.py
