Metadata-Version: 2.0
Name: 2mp4
Version: 1.0.1
Summary: Simple utility to convert your video files into mp4s.
Home-page: https://github.com/skonakov/2mp4.git
Author: Sergey Konakov
Author-email: skonakov@gmail.com
License: MIT
Download-URL: https://github.com/skonakov/2mp4/tarball/1.0.1
Platform: UNKNOWN
Classifier: Intended Audience :: End Users/Desktop
Classifier: License :: OSI Approved :: MIT License
Classifier: Programming Language :: Python
Classifier: Topic :: Multimedia :: Video :: Conversion
Classifier: Operating System :: Unix
Requires-Dist: progressbar2
Requires-Dist: pymediainfo
Requires-Dist: sh
